[{"RoundNumber":1,"ChicksBorn":15,"Pre-Season Rank":80.7142857143,"AvgFederationPos":96.1666666667,"AvgLoftPos":9.8333333333,"AverageRaceIndex":0.393007882,"Top20FedFinishes":0,"FedWins":0,"Loft top 3":0},{"RoundNumber":2,"ChicksBorn":13,"Pre-Season Rank":84.1666666667,"AvgFederationPos":66.875,"AvgLoftPos":6.875,"AverageRaceIndex":0.5803643365,"Top20FedFinishes":1,"FedWins":0,"Loft top 3":2},{"RoundNumber":3,"ChicksBorn":7,"Pre-Season Rank":81.4285714286,"AvgFederationPos":84.75,"AvgLoftPos":9.25,"AverageRaceIndex":0.4320802005,"Top20FedFinishes":0,"FedWins":0,"Loft top 3":0},{"RoundNumber":4,"ChicksBorn":3,"Pre-Season Rank":73.3333333333,"AvgFederationPos":53.0,"AvgLoftPos":6.0,"AverageRaceIndex":0.6378446115,"Top20FedFinishes":0,"FedWins":0,"Loft top 3":0},{"RoundNumber":5,"ChicksBorn":0,"Pre-Season Rank":"","AvgFederationPos":"","AvgLoftPos":"","AverageRaceIndex":"","Top20FedFinishes":0,"FedWins":0,"Loft top 3":0},{"RoundNumber":6,"ChicksBorn":0,"Pre-Season Rank":"","AvgFederationPos":"","AvgLoftPos":"","AverageRaceIndex":"","Top20FedFinishes":0,"FedWins":0,"Loft top 3":0},{"RoundNumber":7,"ChicksBorn":0,"Pre-Season Rank":"","AvgFederationPos":"","AvgLoftPos":"","AverageRaceIndex":"","Top20FedFinishes":0,"FedWins":0,"Loft top 3":0},{"RoundNumber":8,"ChicksBorn":0,"Pre-Season Rank":"","AvgFederationPos":"","AvgLoftPos":"","AverageRaceIndex":"","Top20FedFinishes":0,"FedWins":0,"Loft top 3":0}]